langserve/__init__.py
langserve/callbacks.py
langserve/client.py
langserve/lzstring.py
langserve/playground/dist/assets/index-7c3e1e1d.js
langserve/playground/dist/assets/index-c6cde0dd.css
langserve/playground/dist/favicon.ico
langserve/playground/dist/index.html
langserve/playground.py
langserve/pydantic.py
langserve/schema.py
langserve/serialization.py
langserve/server.py
langserve/validation.py
langserve/version.py
ragstack_ai_langserve-0.0.1a2.dist-info/LICENSE
ragstack_ai_langserve-0.0.1a2.dist-info/METADATA
ragstack_ai_langserve-0.0.1a2.dist-info/WHEEL
ragstack_ai_langserve-0.0.1a2.dist-info/RECORD
